Metadata-Version: 2.1
Name: nisshi
Version: 0.1.1
Summary: another logger library for python
Home-page: https://codeberg.org/daysant/nisshi
Author: daysant
Author-email: daysant@proton.me
License: daysant license v2
Platform: UNKNOWN
